avnBase/__init__.py
avnBase/avn_base.py
kptopic/KPTopic.py
kptopic/__init__.py
kptopic-0.0.13.dist-info/licenses/LICENSE
visBase/__init__.py
visBase/vis_base.py
kptopic-0.0.13.dist-info/METADATA
kptopic-0.0.13.dist-info/WHEEL
kptopic-0.0.13.dist-info/top_level.txt
kptopic-0.0.13.dist-info/RECORD
