Metadata-Version: 2.4
Name: kptopic
Version: 0.0.13
Summary: A semantic topic generator with sentiment score
Author-email: "Peng (Atsaniik) Yang" <peng.yang@uef.fi>
Project-URL: Homepage, https://github.com/Atsaniik/kptopic
Project-URL: Bug Tracker, https://github.com/Atsaniik/kptopic/issues
Classifier: Programming Language :: Python :: 3
Classifier: License :: OSI Approved :: MIT License
Classifier: Operating System :: OS Independent
Requires-Python: >=3.8
License-File: LICENSE
Requires-Dist: networkx
Requires-Dist: matplotlib
Requires-Dist: numpy
Requires-Dist: spacy
Requires-Dist: nltk
Dynamic: license-file
